langchain_greennode/__init__.py
langchain_greennode/chat_models.py
langchain_greennode/embeddings.py
langchain_greennode/reranks.py
langchain_greennode-0.0.1.dist-info/METADATA
langchain_greennode-0.0.1.dist-info/WHEEL
langchain_greennode-0.0.1.dist-info/RECORD
